README.md
pymhash.py
setup.py
pymhash.egg-info/PKG-INFO
pymhash.egg-info/SOURCES.txt
pymhash.egg-info/dependency_links.txt
pymhash.egg-info/requires.txt
pymhash.egg-info/top_level.txt